Workbook

Sheet Assumptions
A1: NEXGEN TECH PVT LTD — MODEL ASSUMPTIONS & DRIVERS
A4: Active Scenario Switch (1=Base, 2=Bull, 3=Bear): | C4: 1
A6: DRIVER CATEGORY | B6: Base | C6: Bull | D6: Bear | E6: Active Value
A7: Annual Revenue Growth Rate | B7: 0.25 | C7: 0.35 | D7: 0.1 | E7: =CHOOSE($C$4, B7, C7, D7) -> 0.25
A8: COGS (% of Revenue) | B8: 0.2 | C8: 0.16 | D8: 0.25 | E8: =CHOOSE($C$4, B8, C8, D8) -> 0.2
A9: Marketing Expense (% of Revenue) | B9: 0.25 | C9: 0.2 | D9: 0.3 | E9: =CHOOSE($C$4, B9, C9, D9) -> 0.25
A10: Tech & Ops Expense (% of Revenue) | B10: 0.18 | C10: 0.15 | D10: 0.22 | E10: =CHOOSE($C$4, B10, C10, D10) -> 0.18
A11: Sales Expense (% of Revenue) | B11: 0.08 | C11: 0.07 | D11: 0.1 | E11: =CHOOSE($C$4, B11, C11, D11) -> 0.08
A12: HR & Admin (Fixed Annual Cost) | B12: 600000 | C12: 600000 | D12: 650000 | E12: =CHOOSE($C$4, B12, C12, D12) -> 600000
A13: Income Tax Rate | B13: 0.25 | C13: 0.25 | D13: 0.25 | E13: =CHOOSE($C$4, B13, C13, D13) -> 0.25
A14: Depreciation Rate (% of PP&E) | B14: 0.1 | C14: 0.1 | D14: 0.1 | E14: =CHOOSE($C$4, B14, C14, D14) -> 0.1
A15: Starting Property, Plant & Equipment (PP&E) | B15: 1000000 | C15: 1000000 | D15: 1000000 | E15: =CHOOSE($C$4, B15,C15,D15) -> 1000000
A16: Starting Long-Term Debt | B16: 625000 | C16: 625000 | D16: 625000 | E16: =CHOOSE($C$4, B16, C16, D16) -> 625000
A17: Interest Rate on Debt | B17: 0.08 | C17: 0.08 | D17: 0.08 | E17: =CHOOSE($C$4, B17, C17, D17) -> 0.08

Sheet Income statement 
A1: NEXGEN TECH PVT LTD — PRO FORMA INCOME STATEMENT
A5: FINANCIAL LINE ITEM | B5: 2026 (Base) | C5: 2027 (Fcst) | D5: 2028 (Fcst) | E5: 2029 (Fcst)
A7: Gross Revenue | B7: 5000000 | C7: =B7 * (1 + Assumptions!$E$7) -> 6250000 | D7: =C7 * (1 + Assumptions!$E$7) -> 7812500 | E7: =D7 * (1 + Assumptions!$E$7) -> 9765625
A8: Cost of Goods Sold (COGS) | B8: 1000000 | C8: =C7*Assumptions!$E$8 -> 1250000 | D8: =D7*Assumptions!$E$8 -> 1562500 | E8: =E7*Assumptions!$E$8 -> 1953125
A9: Gross Profit | B9: =B7-B8 -> 4000000 | C9: =C7-C8 -> 5000000 | D9: =D7-D8 -> 6250000 | E9: =E7-E8 -> 7812500
A10: OPERATING EXPENSES:
A11: Marketing Expense | B11: 1250000 | C11: =C7*Assumptions!$E$9 -> 1562500 | D11: =D7*Assumptions!$E$9 -> 1953125 | E11: =E7*Assumptions!$E$9 -> 2441406.2
A12: Tech & Ops Expense | B12: 900000 | C12: =C7*Assumptions!$E$10 -> 1125000 | D12: =D7*Assumptions!$E$10 -> 1406250 | E12: =E7*Assumptions!$E$10 -> 1757812.5
A13: Sales Expense | B13: 400000 | C13: =C7*Assumptions!$E$11 -> 500000 | D13: =D7*Assumptions!$E$11 -> 625000 | E13: =E7*Assumptions!$E$11 -> 781250
A14: HR & Admin Expense (Fixed) | B14: 600000 | C14: =Assumptions!$E$12 -> 600000 | D14: =Assumptions!$E$12 -> 600000 | E14: =Assumptions!$E$12 -> 600000
A15: Total Operating Expenses | B15: =SUM(B11:B14) -> 3150000 | C15: =SUM(C11:C14) -> 3787500 | D15: =SUM(D11:D14) -> 4584375 | E15: =SUM(E11:E14) -> 5580468.8
A16: EBITDA | B16: =B9-B15 -> 850000 | C16: =C9-C15 -> 1212500 | D16: =D9-D15 -> 1665625 | E16: =E9-E15 -> 2232031.2
A17: Less: Depreciation | B17: 100000 | C17: =Assumptions!$E$15*Assumptions!$E$14 -> 100000 | D17: =Assumptions!$E$15*Assumptions!$E$14 -> 100000 | E17: =Assumptions!$E$15*Assumptions!$E$14 -> 100000
A18: EBIT (Operating Profit) | B18: =B16-B17 -> 750000 | C18: =C16-C17 -> 1112500 | D18: =D16-D17 -> 1565625 | E18: =E16-E17 -> 2132031.2
A19: Less: Interest Expense | B19: 50000 | C19: =Assumptions!$E$16*Assumptions!$E$17 -> 50000 | D19: =Assumptions!$E$16*Assumptions!$E$17 -> 50000 | E19: =Assumptions!$E$16*Assumptions!$E$17 -> 50000
A20: EBT (Pre-Tax Profit) | B20: =B18-B19 -> 700000 | C20: =C18-C19 -> 1062500 | D20: =D18-D19 -> 1515625 | E20: =E18-E19 -> 2082031.2
A21: Less: Income Tax | B21: =B20*0.25 -> 175000 | C21: =IF(C20>0,C20*Assumptions!$E$13,0) -> 265625 | D21: =IF(D20>0,D20*Assumptions!$E$13,0) -> 378906.25 | E21: =IF(E20>0,E20*Assumptions!$E$13,0) -> 520507.81
A22: NET INCOME (Profit After Tax) | B22: =B20-B21 -> 525000 | C22: =C20-C21 -> 796875 | D22: =D20-D21 -> 1136718.8 | E22: =E20-E21 -> 1561523.4

Sheet Balance sheet 
A1: NEXGEN TECH PVT LTD — PRO FORMA BALANCE SHEET
A3: BALANCE SHEET LINE ITEM | B3: 2026 (Base) | C3: 2027 (Fcst) | D3: 2028 (Fcst) | E3: 2029 (Fcst)
A5: ASSETS | B5: AMOUNT(Rs.) | C5: AMOUNT(Rs.) | D5: AMOUNT(Rs.) | E5: AMOUNT(Rs.)
A6: Current Assets:
A7: Cash & Cash Equivalents | B7: 1500000 | C7: =C32-C15-C8 -> 2520162.1 | D7: =D32-D15-D8 -> 3654141.1 | E7: =E32-E15-E8 -> 5187239.9
A8: Accounts Receivable (AR) | B8: 616438 | C8: =('Income statement '!C7/365)*30 -> 513698.63 | D8: =('Income statement '!D7/365)*30 -> 642123.29 | E8: =('Income statement '!E7/365)*30 -> 802654.11
A9: TOTAL CURRENT ASSETS | B9: =SUM(B7:B8) -> 2116438 | C9: =SUM(C7:C8) -> 3033860.7 | D9: =SUM(D7:D8) -> 4296264.4 | E9: =SUM(E7:E8) -> 5989894
A11: Non-Current Assets:
A12: Property, Plant & Equipment (PP&E) | B12: 1000000 | C12: =B12 -> 1000000 | D12: =C12 -> 1000000 | E12: =D12 -> 1000000
A13: Less: Accumulated Depreciation | B13: 100000 | C13: =B13+'Income statement '!C17 -> 200000 | D13: =C13+'Income statement '!D17 -> 300000 | E13: =D13+'Income statement '!E17 -> 400000
A14: NET PP&E | B14: =B12-B13 -> 900000 | C14: =C12-C13 -> 800000 | D14: =D12-D13 -> 700000 | E14: =E12-E13 -> 600000
A15: TOTAL NON-CURRENT ASSETS | B15: =B14 -> 900000 | C15: =C14 -> 800000 | D15: =D14 -> 700000 | E15: =E14 -> 600000
A16: TOTAL ASSETS | B16: =B9+B14 -> 3016438 | C16: =C9+C15 -> 3833860.7 | D16: =D9+D15 -> 4996264.4 | E16: =E9+E15 -> 6589894
A18: LIABILITIES & EQUITY
A19: Current Liabilities:
A20: Accounts Payable (AP) | B20: 82192 | C20: =('Income statement '!C8/365)*30 -> 102739.73 | D20: =('Income statement '!D8/365)*30 -> 128424.66 | E20: =('Income statement '!E8/365)*30 -> 160530.82
A21: TOTAL CURRENT LIABILITIES | B21: =B20 -> 82192 | C21: =C20 -> 102739.73 | D21: =D20 -> 128424.66 | E21: =E20 -> 160530.82
A23: Non-Current Liabilities:
A24: Long-Term Debt | B24: 625000 | C24: =B24 -> 625000 | D24: =C24 -> 625000 | E24: =D24 -> 625000
A25: TOTAL NON-CURRENT LIABILITIES | B25: =B24 -> 625000 | C25: =C24 -> 625000 | D25: =D24 -> 625000 | E25: =E24 -> 625000
A26: TOTAL LIABILITIES | B26: =B24+B21 -> 707192 | C26: =C21+C25 -> 727739.73 | D26: =D21+D25 -> 753424.66 | E26: =E21+E25 -> 785530.82
A28: Shareholders' Equity:
A29: Common Stock / Share Capital | B29: 1000000 | C29: =B29 -> 1000000 | D29: =C29 -> 1000000 | E29: =D29 -> 1000000
A30: Retained Earnings | B30: 1309246 | C30: =B30+'Income statement '!C22 -> 2106121 | D30: =C30+'Income statement '!D22 -> 3242839.8 | E30: =D30+'Income statement '!E22 -> 4804363.2
A31: TOTAL SHAREHOLDERS' EQUITY | B31: =SUM(B29:B30) -> 2309246 | C31: =SUM(C29:C30) -> 3106121 | D31: =SUM(D29:D30) -> 4242839.8 | E31: =SUM(E29:E30) -> 5804363.2
A32: TOTAL LIABILITIES & EQUITY | B32: =B26+B31 -> 3016438 | C32: =C26+C31 -> 3833860.7 | D32: =D26+D31 -> 4996264.4 | E32: =E26+E31 -> 6589894

Sheet Cashflow

Sheet DCF valuation 
